podfeed/__init__.py
podfeed/client.py
podfeed/exceptions.py
podfeed/types.py
podfeed_sdk-0.3.0.dist-info/METADATA
podfeed_sdk-0.3.0.dist-info/WHEEL
podfeed_sdk-0.3.0.dist-info/top_level.txt
podfeed_sdk-0.3.0.dist-info/RECORD
