Metadata-Version: 2.4
Name: podfeed-sdk
Version: 0.3.0
Summary: A Python SDK for the PodFeed API
Home-page: https://github.com/smh-labs/podfeed-sdk-samples
Author: PodFeed
Author-email: PodFeed <api-support@podfeed.ai>
License: MIT
Project-URL: Homepage, https://podfeed.ai
Project-URL: Repository, https://github.com/podfeed/podfeed-sdk-python
Project-URL: Bug Reports, https://github.com/podfeed/podfeed-sdk-python/issues
Classifier: Development Status :: 4 - Beta
Classifier: Intended Audience :: Developers
Classifier: License :: OSI Approved :: MIT License
Classifier: Operating System :: OS Independent
Classifier: Programming Language :: Python :: 3
Classifier: Programming Language :: Python :: 3.7
Classifier: Programming Language :: Python :: 3.8
Classifier: Programming Language :: Python :: 3.9
Classifier: Programming Language :: Python :: 3.10
Classifier: Programming Language :: Python :: 3.11
Requires-Python: >=3.7
Requires-Dist: requests>=2.25.0
Requires-Dist: pydantic<3.0.0,>=1.10.0
Provides-Extra: dev
Requires-Dist: pytest>=6.0; extra == "dev"
Requires-Dist: pytest-cov>=2.0; extra == "dev"
Requires-Dist: black>=22.0; extra == "dev"
Requires-Dist: flake8>=4.0; extra == "dev"
Requires-Dist: mypy>=0.910; extra == "dev"
Dynamic: author
Dynamic: home-page
Dynamic: requires-python
